bannerpy/__init__.py
bannerpy/cards.py
bannerpy/fields.py
bannerpy-0.1.0.dist-info/METADATA
bannerpy-0.1.0.dist-info/WHEEL
bannerpy-0.1.0.dist-info/RECORD
