Metadata-Version: 2.1
Name: bannerpy
Version: 0.1.0
Summary: Parametric "card" generator for media like video or image. BannerPy can be used to generate image "cards" that can be used for things like name cards, title cards, and on-screen notes and citations.
License: GPL v3.0
Author: Ben Rankin
Author-email: me@benrank.in
Requires-Python: >=3.11,<4.0
Classifier: License :: Other/Proprietary License
Classifier: Programming Language :: Python :: 3
Classifier: Programming Language :: Python :: 3.11
Classifier: Programming Language :: Python :: 3.12
Classifier: Programming Language :: Python :: 3.13
Requires-Dist: PyYAML (>=6.0.2,<7.0.0)
Requires-Dist: pixie-python (>=4.3.0,<5.0.0)
